{"color":"#336699","name":"Carlos E. Gon...","data":{"first_name":"Carlos E.","university_url":"http://www.anbg.gov.au/cpbr/staff/gonzalez-orozco-carlos-staff.html","email":"","social":"","last_name":"González-Orozco","node_source":"Web","node_type":"Researcher","have_grants":false,"full_name":"Carlos E. González-Orozco"},"children":[{"color":"#123456","name":"doi:10.5061/d...","data":{"node_source":"Dryad","node_type":"Dataset","doi":"doi:10.5061/dryad.dv4qk"},"class":"Dataset","self":"http://localhost:7474/db/data/node/141250","size":1},{"color":"#123456","name":"doi:10.5061/d...","data":{"node_source":"Dryad","node_type":"Dataset","doi":"doi:10.5061/dryad.33kn3"},"class":"Dataset","self":"http://localhost:7474/db/data/node/141249","size":1}],"class":"Researcher","self":"http://localhost:7474/db/data/node/141248","size":1}