{"color":"#336699","name":"Alexandre Fou...","data":{"first_name":"Alexandre","university_url":"http://www.genetics.unimelb.edu.au/person/academics/alexfl.html","email":"","social":"","last_name":"Fournier-Level","node_source":"Web","node_type":"Researcher","have_grants":false,"full_name":"Alexandre Fournier-Level"},"children":[{"color":"#123456","name":"doi:10.5061/d...","data":{"node_source":"Dryad","node_type":"Dataset","doi":"doi:10.5061/dryad.37f9t"},"class":"Dataset","self":"http://localhost:7474/db/data/node/141231","size":1},{"color":"#123456","name":"doi:10.5061/d...","data":{"node_source":"Dryad","node_type":"Dataset","doi":"doi:10.5061/dryad.1pg3n"},"class":"Dataset","self":"http://localhost:7474/db/data/node/141230","size":1}],"class":"Researcher","self":"http://localhost:7474/db/data/node/141229","size":1}