{"color":"#336699","name":"Dr Megha Kaushik","data":{"first_name":"Megha","title":"Dr","dw_individual_id":"5046677","middle_name":"","last_name":"Kaushik","source_individual_id":"5046677","node_source":"NHMRC","node_type":"Researcher","source_system":"RGMS","full_name":"Dr Megha Kaushik"},"children":[{"color":"#FF4D4D","name":"Investigating...","data":{"media_summary":"","end_year":2014,"keywords":["optic neuritis","glaucoma","neurodegeneration","synaptic mechanisms","visual pathways"],"nhmrc_grant_id":1056517,"application_year":2012,"health_keywords":["vision loss","visual system","retinal degeneration"],"scientific_title":"Investigating trans-synaptic degeneration in the human visual pathway","start_year":2013,"node_source":"NHMRC","node_type":"Grant","field_of_research":"Ophthalmology","research_area":"Clinical Medicine and Science","for_category":"OPHTHALMOLOGY and OPTOMETRY","cia_name":"Dr Megha Kaushik","higher_grant_type":"NHMRC Postgraduate Scholarships","purl":"http://purl.org/au-research/grants/nhmrc/1056517","simplified_title":"Trans-synaptic degeneration in the human visual pathway","sub_type":"Medical/Dental Postgraduate Scholarship","total_budget":"79514.86","source_system":"This research project investigates the spread of neuronal damage along the visual pathway from the retina to higher order areas including the visual cortex and inter-hemispheric tracts.  This trans-synaptic degeneration will be examined in Leber's optic atrophy, optic neuritis and glaucoma."},"children":[{"color":"#0066FF","name":"University of...","data":{"source":"NHMRC","name":"University of Sydney","state":"NSW","nla":"http://nla.gov.au/nla.party-593941","type":"University","node_source":"NHMRC","node_type":"Institution"},"class":"Institution","self":"http://localhost:7474/db/data/node/13","size":1}],"class":"Grant","self":"http://localhost:7474/db/data/node/74894","size":1}],"class":"Researcher","self":"http://localhost:7474/db/data/node/76275","size":1}